mujoco_animator/__init__.py
mujoco_animator/animator.py
mujoco_animator/cli.py
mujoco_animator/convert.py
mujoco_animator/format.py
mujoco_animator/py.typed
mujoco_animator/viewer.py
mujoco_animator-0.0.3.dist-info/licenses/LICENSE
mujoco_animator-0.0.3.dist-info/METADATA
mujoco_animator-0.0.3.dist-info/WHEEL
mujoco_animator-0.0.3.dist-info/entry_points.txt
mujoco_animator-0.0.3.dist-info/top_level.txt
mujoco_animator-0.0.3.dist-info/RECORD
