Metadata-Version: 2.4
Name: mujoco-animator
Version: 0.0.3
Summary: The mujoco-animator project
Home-page: https://github.com/kscalelabs/mujoco-animator
Author: K-Scale Labs
Requires-Python: >=3.11
License-File: LICENSE
Requires-Dist: numpy
Requires-Dist: scipy
Provides-Extra: cli
Requires-Dist: glfw; extra == "cli"
Requires-Dist: mujoco; extra == "cli"
Requires-Dist: mujoco-scenes; extra == "cli"
Requires-Dist: PySide6==6.9.0; extra == "cli"
Provides-Extra: dev
Requires-Dist: mypy; extra == "dev"
Requires-Dist: pytest; extra == "dev"
Requires-Dist: ruff; extra == "dev"
Provides-Extra: all
Requires-Dist: glfw; extra == "all"
Requires-Dist: mujoco; extra == "all"
Requires-Dist: mujoco-scenes; extra == "all"
Requires-Dist: PySide6==6.9.0; extra == "all"
Requires-Dist: mypy; extra == "all"
Requires-Dist: pytest; extra == "all"
Requires-Dist: ruff; extra == "all"
Dynamic: author
Dynamic: description
Dynamic: description-content-type
Dynamic: home-page
Dynamic: license-file
Dynamic: provides-extra
Dynamic: requires-dist
Dynamic: requires-python
Dynamic: summary
